pollenisator_gui-2.7.10.4.dist-info/licenses/LICENSE
pollenisatorgui/__init__.py
pollenisatorgui/autoscanworker.py
pollenisatorgui/pollenisator.py
pollenisatorgui/pollex.py
pollenisatorgui/pollterminal.py
pollenisatorgui/pollworker.py
pollenisatorgui/config/.Xresources
pollenisatorgui/config/.tmux.conf
pollenisatorgui/config/clientSample.cfg
pollenisatorgui/config/settings.cfg
pollenisatorgui/config/shell_ressources/bash_setupTerminalForPentest_notrap.sh
pollenisatorgui/config/shell_ressources/bash_setupTerminalForPentest_trap.sh
pollenisatorgui/config/shell_ressources/zshrc_notrap/.zshrc
pollenisatorgui/config/shell_ressources/zshrc_trap/.zshrc
pollenisatorgui/config/tools.d/tools.json
pollenisatorgui/core/__init__.py
pollenisatorgui/core/application/CollapsibleFrame.py
pollenisatorgui/core/application/__init__.py
pollenisatorgui/core/application/appli.py
pollenisatorgui/core/application/checkboxscrollabletreeview.py
pollenisatorgui/core/application/mdframe.py
pollenisatorgui/core/application/paginable.py
pollenisatorgui/core/application/pollenisatorentry.py
pollenisatorgui/core/application/pseudotermframe.py
pollenisatorgui/core/application/scrollableframexplateform.py
pollenisatorgui/core/application/scrollabletreeview.py
pollenisatorgui/core/application/statusbar.py
pollenisatorgui/core/application/terminalswidget.py
pollenisatorgui/core/application/dialogs/ChildDialogAskFile.py
pollenisatorgui/core/application/dialogs/ChildDialogAskText.py
pollenisatorgui/core/application/dialogs/ChildDialogAutoScanParams.py
pollenisatorgui/core/application/dialogs/ChildDialogCombo.py
pollenisatorgui/core/application/dialogs/ChildDialogConnect.py
pollenisatorgui/core/application/dialogs/ChildDialogCustomCommand.py
pollenisatorgui/core/application/dialogs/ChildDialogDate.py
pollenisatorgui/core/application/dialogs/ChildDialogDefectView.py
pollenisatorgui/core/application/dialogs/ChildDialogEditCommandSettings.py
pollenisatorgui/core/application/dialogs/ChildDialogEditPassword.py
pollenisator_gui-2.7.10.4.dist-info/METADATA
pollenisator_gui-2.7.10.4.dist-info/WHEEL
pollenisator_gui-2.7.10.4.dist-info/entry_points.txt
pollenisator_gui-2.7.10.4.dist-info/top_level.txt
pollenisator_gui-2.7.10.4.dist-info/RECORD
