Metadata-Version: 2.4
Name: pollenisator-gui
Version: 2.7.10.4
Summary: Pollenisator Client GUI
Home-page: https://github.com/AlgoSecure/PollenisatorGUI
Author: AlgoSecure
Author-email: pollenisator@algosecure.fr
Project-URL: Bug Reports, https://github.com/AlgoSecure/PollenisatorGUI/issues
Project-URL: Source, https://github.com/AlgoSecure/PollenisatorGUI/
Keywords: security tools
Classifier: Development Status :: 4 - Beta
Classifier: Intended Audience :: Information Technology
Classifier: Intended Audience :: System Administrators
Classifier: Topic :: Security
Classifier: Topic :: System :: Networking :: Monitoring
Classifier: License :: OSI Approved :: GNU General Public License v3 (GPLv3)
Classifier: Programming Language :: Python :: 3
Classifier: Programming Language :: Python :: 3.7
Classifier: Programming Language :: Python :: 3.9
Requires-Python: >=3.7
License-File: LICENSE
Requires-Dist: setuptools
Requires-Dist: cryptography>=2.5
Requires-Dist: dnspython
Requires-Dist: feedparser
Requires-Dist: lark-parser>=0.7.8
Requires-Dist: netaddr>=0.7.19
Requires-Dist: Pillow>=6.0.0
Requires-Dist: pyperclip
Requires-Dist: python-jose>=3.3.0
Requires-Dist: requests>=2.18.4
Requires-Dist: pymongo
Requires-Dist: docker
Requires-Dist: python-socketio[client]
Requires-Dist: ttkwidgets
Requires-Dist: watchdog
Requires-Dist: tkinterdnd2-universal
Requires-Dist: customtkinter==5.1.2
Requires-Dist: libtmux
Requires-Dist: tkintermd
Requires-Dist: psutil
Requires-Dist: neo4j
Requires-Dist: screeninfo
Requires-Dist: pygments
Requires-Dist: openpyxl
Requires-Dist: urllib3
Dynamic: author
Dynamic: author-email
Dynamic: classifier
Dynamic: description
Dynamic: description-content-type
Dynamic: home-page
Dynamic: keywords
Dynamic: license-file
Dynamic: project-url
Dynamic: requires-dist
Dynamic: requires-python
Dynamic: summary
